spotiwise/__init__.py
spotiwise/client.py
spotiwise/constants.py
spotiwise/exceptions.py
spotiwise/oauth2.py
spotiwise/object_classes.py
spotiwise/util.py
spotiwise-0.10.8.dist-info/LICENSE.md
spotiwise-0.10.8.dist-info/WHEEL
spotiwise-0.10.8.dist-info/METADATA
spotiwise-0.10.8.dist-info/RECORD
